jikji/__init__.py
jikji/__main__.py
jikji/app.py
jikji/cli.py
jikji/cprint.py
jikji/generator.py
jikji/listener.py
jikji/publisher.py
jikji/utils.py
jikji/view.py
jikji/sample_proj/pages.py
jikji/sample_proj/settings.py
jikji/sample_proj/__pycache__/pages.cpython-36.pyc
jikji/sample_proj/__pycache__/settings.cpython-36.pyc
jikji/sample_proj/static/stylesheet.css
jikji/sample_proj/static/images/image1.jpg
jikji/sample_proj/static/images/image2.jpg
jikji/sample_proj/static/images/image3.jpg
jikji/sample_proj/static/images/image4.jpg
jikji/sample_proj/static/images/image5.jpg
jikji/sample_proj/templates/gallery.html
jikji/sample_proj/templates/home.html
jikji/sample_proj/views/gallery.py
jikji/sample_proj/views/home.py
jikji/sample_proj/views/__pycache__/gallery.cpython-36.pyc
jikji/sample_proj/views/__pycache__/home.cpython-36.pyc
jikji/sample_proj/views/__pycache__/index.cpython-36.pyc
jikji/sample_proj/views/__pycache__/submission_view.cpython-36.pyc
jikji-2.2.4.dist-info/METADATA
jikji-2.2.4.dist-info/RECORD
jikji-2.2.4.dist-info/WHEEL
jikji-2.2.4.dist-info/entry_points.txt
jikji-2.2.4.dist-info/top_level.txt
